Workbook
Name AreaCodes: areas!$A$2:$A$47

Sheet calculator
A1: HRM area rate cost calculator
A2: Bill year 2025. Every charge below is a live formula against the rates sheet.
A3: Calculation_Type 'Rate' is dollars per $100 of taxable assessment; 'Flat Rate' is a fixed dollar charge per property.
A5: Scenario A: Residential
A6: Assessment ($) | B6: 325000
A7: Property class | B7: Residential
A9: Area code | B9: Description | C9: Lookup key | D9: Rate | E9: Calc type | F9: Charge ($) | G9: Share % | H9: Note
A10: M050 | B10: =IF($A10="","",IFERROR(INDEX(areas!$B$2:$B$47,MATCH($A10,areas!$A$2:$A$47,0)),"unknown code")) | C10: =IF($A10="","",$A10&"|"&$B$7) | D10: =IF($C10="","",IFERROR(INDEX(rates!$C$2:$C$166,MATCH($C10,rates!$F$2:$F$166,0)),"")) | E10: =IF($C10="","",IFERROR(INDEX(rates!$D$2:$D$166,MATCH($C10,rates!$F$2:$F$166,0)),"")) | F10: =IF($A10="","",IFERROR(ROUND(IF($E10="Flat Rate",$D10,$D10*$B$6/100),2),0)) | G10: =IF($A10="","",IF($F$16=0,0,ROUND(100*$F10/$F$16,1))) | H10: =IF($A10="","",IF(ISNA(MATCH($C10,rates!$F$2:$F$166,0)),"no 2025 rate for this code and class",""))
A11: M060 | B11: =IF($A11="","",IFERROR(INDEX(areas!$B$2:$B$47,MATCH($A11,areas!$A$2:$A$47,0)),"unknown code")) | C11: =IF($A11="","",$A11&"|"&$B$7) | D11: =IF($C11="","",IFERROR(INDEX(rates!$C$2:$C$166,MATCH($C11,rates!$F$2:$F$166,0)),"")) | E11: =IF($C11="","",IFERROR(INDEX(rates!$D$2:$D$166,MATCH($C11,rates!$F$2:$F$166,0)),"")) | F11: =IF($A11="","",IFERROR(ROUND(IF($E11="Flat Rate",$D11,$D11*$B$6/100),2),0)) | G11: =IF($A11="","",IF($F$16=0,0,ROUND(100*$F11/$F$16,1))) | H11: =IF($A11="","",IF(ISNA(MATCH($C11,rates!$F$2:$F$166,0)),"no 2025 rate for this code and class",""))
A12: A000 | B12: =IF($A12="","",IFERROR(INDEX(areas!$B$2:$B$47,MATCH($A12,areas!$A$2:$A$47,0)),"unknown code")) | C12: =IF($A12="","",$A12&"|"&$B$7) | D12: =IF($C12="","",IFERROR(INDEX(rates!$C$2:$C$166,MATCH($C12,rates!$F$2:$F$166,0)),"")) | E12: =IF($C12="","",IFERROR(INDEX(rates!$D$2:$D$166,MATCH($C12,rates!$F$2:$F$166,0)),"")) | F12: =IF($A12="","",IFERROR(ROUND(IF($E12="Flat Rate",$D12,$D12*$B$6/100),2),0)) | G12: =IF($A12="","",IF($F$16=0,0,ROUND(100*$F12/$F$16,1))) | H12: =IF($A12="","",IF(ISNA(MATCH($C12,rates!$F$2:$F$166,0)),"no 2025 rate for this code and class",""))
B13: =IF($A13="","",IFERROR(INDEX(areas!$B$2:$B$47,MATCH($A13,areas!$A$2:$A$47,0)),"unknown code")) | C13: =IF($A13="","",$A13&"|"&$B$7) | D13: =IF($C13="","",IFERROR(INDEX(rates!$C$2:$C$166,MATCH($C13,rates!$F$2:$F$166,0)),"")) | E13: =IF($C13="","",IFERROR(INDEX(rates!$D$2:$D$166,MATCH($C13,rates!$F$2:$F$166,0)),"")) | F13: =IF($A13="","",IFERROR(ROUND(IF($E13="Flat Rate",$D13,$D13*$B$6/100),2),0)) | G13: =IF($A13="","",IF($F$16=0,0,ROUND(100*$F13/$F$16,1))) | H13: =IF($A13="","",IF(ISNA(MATCH($C13,rates!$F$2:$F$166,0)),"no 2025 rate for this code and class",""))
B14: =IF($A14="","",IFERROR(INDEX(areas!$B$2:$B$47,MATCH($A14,areas!$A$2:$A$47,0)),"unknown code")) | C14: =IF($A14="","",$A14&"|"&$B$7) | D14: =IF($C14="","",IFERROR(INDEX(rates!$C$2:$C$166,MATCH($C14,rates!$F$2:$F$166,0)),"")) | E14: =IF($C14="","",IFERROR(INDEX(rates!$D$2:$D$166,MATCH($C14,rates!$F$2:$F$166,0)),"")) | F14: =IF($A14="","",IFERROR(ROUND(IF($E14="Flat Rate",$D14,$D14*$B$6/100),2),0)) | G14: =IF($A14="","",IF($F$16=0,0,ROUND(100*$F14/$F$16,1))) | H14: =IF($A14="","",IF(ISNA(MATCH($C14,rates!$F$2:$F$166,0)),"no 2025 rate for this code and class",""))
B15: =IF($A15="","",IFERROR(INDEX(areas!$B$2:$B$47,MATCH($A15,areas!$A$2:$A$47,0)),"unknown code")) | C15: =IF($A15="","",$A15&"|"&$B$7) | D15: =IF($C15="","",IFERROR(INDEX(rates!$C$2:$C$166,MATCH($C15,rates!$F$2:$F$166,0)),"")) | E15: =IF($C15="","",IFERROR(INDEX(rates!$D$2:$D$166,MATCH($C15,rates!$F$2:$F$166,0)),"")) | F15: =IF($A15="","",IFERROR(ROUND(IF($E15="Flat Rate",$D15,$D15*$B$6/100),2),0)) | G15: =IF($A15="","",IF($F$16=0,0,ROUND(100*$F15/$F$16,1))) | H15: =IF($A15="","",IF(ISNA(MATCH($C15,rates!$F$2:$F$166,0)),"no 2025 rate for this code and class",""))
A16: Total | F16: =SUM(F10:F15) | G16: =IF($F$16=0,0,ROUND(100*$F$16/$F$16,1))
A18: Scenario B: Commercial
A19: Assessment ($) | B19: 600000
A20: Property class | B20: Commercial
A22: Area code | B22: Description | C22: Lookup key | D22: Rate | E22: Calc type | F22: Charge ($) | G22: Share % | H22: Note
A23: M050 | B23: =IF($A23="","",IFERROR(INDEX(areas!$B$2:$B$47,MATCH($A23,areas!$A$2:$A$47,0)),"unknown code")) | C23: =IF($A23="","",$A23&"|"&$B$20) | D23: =IF($C23="","",IFERROR(INDEX(rates!$C$2:$C$166,MATCH($C23,rates!$F$2:$F$166,0)),"")) | E23: =IF($C23="","",IFERROR(INDEX(rates!$D$2:$D$166,MATCH($C23,rates!$F$2:$F$166,0)),"")) | F23: =IF($A23="","",IFERROR(ROUND(IF($E23="Flat Rate",$D23,$D23*$B$19/100),2),0)) | G23: =IF($A23="","",IF($F$29=0,0,ROUND(100*$F23/$F$29,1))) | H23: =IF($A23="","",IF(ISNA(MATCH($C23,rates!$F$2:$F$166,0)),"no 2025 rate for this code and class",""))
A24: R000 | B24: =IF($A24="","",IFERROR(INDEX(areas!$B$2:$B$47,MATCH($A24,areas!$A$2:$A$47,0)),"unknown code")) | C24: =IF($A24="","",$A24&"|"&$B$20) | D24: =IF($C24="","",IFERROR(INDEX(rates!$C$2:$C$166,MATCH($C24,rates!$F$2:$F$166,0)),"")) | E24: =IF($C24="","",IFERROR(INDEX(rates!$D$2:$D$166,MATCH($C24,rates!$F$2:$F$166,0)),"")) | F24: =IF($A24="","",IFERROR(ROUND(IF($E24="Flat Rate",$D24,$D24*$B$19/100),2),0)) | G24: =IF($A24="","",IF($F$29=0,0,ROUND(100*$F24/$F$29,1))) | H24: =IF($A24="","",IF(ISNA(MATCH($C24,rates!$F$2:$F$166,0)),"no 2025 rate for this code and class",""))
A25: A020 | B25: =IF($A25="","",IFERROR(INDEX(areas!$B$2:$B$47,MATCH($A25,areas!$A$2:$A$47,0)),"unknown code")) | C25: =IF($A25="","",$A25&"|"&$B$20) | D25: =IF($C25="","",IFERROR(INDEX(rates!$C$2:$C$166,MATCH($C25,rates!$F$2:$F$166,0)),"")) | E25: =IF($C25="","",IFERROR(INDEX(rates!$D$2:$D$166,MATCH($C25,rates!$F$2:$F$166,0)),"")) | F25: =IF($A25="","",IFERROR(ROUND(IF($E25="Flat Rate",$D25,$D25*$B$19/100),2),0)) | G25: =IF($A25="","",IF($F$29=0,0,ROUND(100*$F25/$F$29,1))) | H25: =IF($A25="","",IF(ISNA(MATCH($C25,rates!$F$2:$F$166,0)),"no 2025 rate for this code and class",""))
B26: =IF($A26="","",IFERROR(INDEX(areas!$B$2:$B$47,MATCH($A26,areas!$A$2:$A$47,0)),"unknown code")) | C26: =IF($A26="","",$A26&"|"&$B$20) | D26: =IF($C26="","",IFERROR(INDEX(rates!$C$2:$C$166,MATCH($C26,rates!$F$2:$F$166,0)),"")) | E26: =IF($C26="","",IFERROR(INDEX(rates!$D$2:$D$166,MATCH($C26,rates!$F$2:$F$166,0)),"")) | F26: =IF($A26="","",IFERROR(ROUND(IF($E26="Flat Rate",$D26,$D26*$B$19/100),2),0)) | G26: =IF($A26="","",IF($F$29=0,0,ROUND(100*$F26/$F$29,1))) | H26: =IF($A26="","",IF(ISNA(MATCH($C26,rates!$F$2:$F$166,0)),"no 2025 rate for this code and class",""))
B27: =IF($A27="","",IFERROR(INDEX(areas!$B$2:$B$47,MATCH($A27,areas!$A$2:$A$47,0)),"unknown code")) | C27: =IF($A27="","",$A27&"|"&$B$20) | D27: =IF($C27="","",IFERROR(INDEX(rates!$C$2:$C$166,MATCH($C27,rates!$F$2:$F$166,0)),"")) | E27: =IF($C27="","",IFERROR(INDEX(rates!$D$2:$D$166,MATCH($C27,rates!$F$2:$F$166,0)),"")) | F27: =IF($A27="","",IFERROR(ROUND(IF($E27="Flat Rate",$D27,$D27*$B$19/100),2),0)) | G27: =IF($A27="","",IF($F$29=0,0,ROUND(100*$F27/$F$29,1))) | H27: =IF($A27="","",IF(ISNA(MATCH($C27,rates!$F$2:$F$166,0)),"no 2025 rate for this code and class",""))
B28: =IF($A28="","",IFERROR(INDEX(areas!$B$2:$B$47,MATCH($A28,areas!$A$2:$A$47,0)),"unknown code")) | C28: =IF($A28="","",$A28&"|"&$B$20) | D28: =IF($C28="","",IFERROR(INDEX(rates!$C$2:$C$166,MATCH($C28,rates!$F$2:$F$166,0)),"")) | E28: =IF($C28="","",IFERROR(INDEX(rates!$D$2:$D$166,MATCH($C28,rates!$F$2:$F$166,0)),"")) | F28: =IF($A28="","",IFERROR(ROUND(IF($E28="Flat Rate",$D28,$D28*$B$19/100),2),0)) | G28: =IF($A28="","",IF($F$29=0,0,ROUND(100*$F28/$F$29,1))) | H28: =IF($A28="","",IF(ISNA(MATCH($C28,rates!$F$2:$F$166,0)),"no 2025 rate for this code and class",""))
A29: Total | F29: =SUM(F23:F28) | G29: =IF($F$29=0,0,ROUND(100*$F$29/$F$29,1))

Sheet rates
A1: Rate_Code | B1: Rate_Type | C1: Rate | D1: Calculation_Type | E1: Rate_Description | F1: key
A2: A000 | B2: Residential | C2: 45 | D2: Flat Rate | E2: FRAME SUB HOMEOWNERS RES | F2: =A2&"|"&B2
A3: A000 | B3: Resource | C3: 45 | D3: Flat Rate | E3: FRAME SUB HOMEOWNERS RES | F3: =A3&"|"&B3
A4: A010 | B4: Residential | C4: 0.023 | D4: Rate | E4: HALIBURTON/HIGHBURY REC RES | F4: =A4&"|"&B4
A5: A010 | B5: Resource | C5: 0.023 | D5: Rate | E5: HALIBURTON/HIGHBURY RE RESO | F5: =A5&"|"&B5
A6: A020 | B6: Commercial | C6: 100 | D6: Flat Rate | E6: SILVERSIDES RESIDENTS RES | F6: =A6&"|"&B6
A7: A020 | B7: Residential | C7: 100 | D7: Flat Rate | E7: SILVERSIDES RESIDENTS RES | F7: =A7&"|"&B7
A8: A020 | B8: Resource | C8: 100 | D8: Flat Rate | E8: SILVERSIDES RESIDENTS RES | F8: =A8&"|"&B8
A9: A030 | B9: Residential | C9: 0.005 | D9: Rate | E9: HIGHLAND PARK REC ASSOC RES | F9: =A9&"|"&B9
A10: A030 | B10: Resource | C10: 0.005 | D10: Rate | E10: HIGHLAND PARK REC ASSO RESO | F10: =A10&"|"&B10
A11: A040 | B11: Commercial | C11: 50 | D11: Flat Rate | E11: KINGSWOOD RATEPAYERS RES | F11: =A11&"|"&B11
A12: A040 | B12: Residential | C12: 50 | D12: Flat Rate | E12: KINGSWOOD RATEPAYERS RES | F12: =A12&"|"&B12
A13: A040 | B13: Resource | C13: 50 | D13: Flat Rate | E13: KINGSWOOD RATEPAYERS RES | F13: =A13&"|"&B13
... A166: R220 | B166: Resource | C166: 250 | D166: Flat Rate | E166: GILL COVE RD MAINT RES | F166: =A166&"|"&B166

Sheet areas
A1: AREARATE_CODE | B1: DESCRIP | C1: category
A2: A000 | B2: Frame Subdivision Homeowners Association | C2: Community Facilities and Services
A3: A010 | B3: Haliburton Highbury Homeowners Association | C3: Community Facilities and Services
A4: A020 | B4: Silversides Residents Association | C4: Community Facilities and Services
A5: A030 | B5: Highland Park Rate Payers Association | C5: Community Facilities and Services
A6: A040 | B6: Kingswood Ratepayers Association | C6: Community Facilities and Services
A7: A050 | B7: Lakeview/Windsor Junction/Fall River Recreation | C7: Community Facilities and Services
A8: A070 | B8: Mineville Community Association | C8: Community Facilities and Services
A9: A080 | B9: Musquodoboit Harbour Common Rate | C9: Community Facilities and Services
A10: A090 | B10: Prospect Road Recreation Association | C10: Community Facilities and Services
A11: A100 | B11: Sackville Heights Community Recreation Centre | C11: Community Facilities and Services
A12: A110 | B12: Fox Hollow Homeowners Association | C12: Community Facilities and Services
... A47: R220 | B47: Gill Cove Road Private Road Maintenance | C47: Private Road
