Workbook

Sheet Data
A1: report_year | B1: co_ops_reporting | C1: total_income | D1: total_expenses | E1: net_income | F1: total_assets | G1: total_liability | H1: total_equity | I1: full_time_employees | J1: part_time_employees | K1: total_employees | L1: total_members
A2: 2015 | B2: 303 | C2: 367161018 | D2: 367742166 | E2: -581148 | F2: 273449067 | G2: 158965531 | H2: 114483534 | I2: 888 | J2: 951 | K2: 1839 | L2: 45726
A3: 2016 | B3: 302 | C3: 428879455 | D3: 439069324 | E3: -10189869 | F3: 255954629 | G3: 156078953 | H3: 99875675 | I3: 916 | J3: 745 | K3: 1661 | L3: 41588
A4: 2017 | B4: 300 | C4: 279434336 | D4: 275343527 | E4: 4090809 | F4: 166898915 | G4: 97358671 | H4: 69540246 | I4: 674 | J4: 782 | K4: 1456 | L4: 42218
A5: 2018 | B5: 299 | C5: 350991616 | D5: 329021557 | E5: 21970059 | F5: 184721435 | G5: 98974460 | H5: 85746976 | I5: 657 | J5: 646 | K5: 1303 | L5: 42769
A6: 2019 | B6: 283 | C6: 332280383 | D6: 325261196 | E6: 7019187 | F6: 168112007 | G6: 86546669 | H6: 81565335 | I6: 747 | J6: 568 | K6: 1315 | L6: 37317
A7: 2020 | B7: 269 | C7: 303121690 | D7: 293311249 | E7: 9810440 | F7: 166825644 | G7: 82829067 | H7: 84042252 | I7: 852 | J7: 565 | K7: 1417 | L7: 41907
A8: 2021 | B8: 259 | C8: 308419823 | D8: 294010202 | E8: 14409622 | F8: 184597862 | G8: 86243125 | H8: 98354734 | I8: 722 | J8: 656 | K8: 1378 | L8: 40715
A9: 2022 | B9: 248 | C9: 297479335 | D9: 289930809 | E9: 7548526 | F9: 191056476 | G9: 88733679 | H9: 102322798 | I9: 762 | J9: 591 | K9: 1353 | L9: 39101
A10: 2023 | B10: 245 | C10: 333850260 | D10: 327105167 | E10: 6745093 | F10: 238566093 | G10: 135069297 | H10: 103496799 | I10: 862 | J10: 586 | K10: 1448 | L10: 43349
A11: 2024 | B11: 226 | C11: 334126998 | D11: 328789797 | E11: 5337201 | F11: 268476908 | G11: 163131045 | H11: 105345863 | I11: 790 | J11: 546 | K11: 1336 | L11: 40740

Sheet Model
A1: Co-op sector financial health
A2: Nova Scotia Co-operatives Financial and Operating Summary, report years 2015 to 2024. Ratios cover the co-ops that reported each year.
A4: Year | B4: Total income ($) | C4: Total expenses ($) | D4: Net income ($) | E4: Operating margin (%) | F4: Margin YoY | G4: Equity ratio (%) | H4: Equity YoY | I4: Solvency (assets / liabilities) | J4: Employees per reporting co-op | K4: Employees YoY
A5: =Data!A2 | B5: =Data!C2 | C5: =Data!D2 | D5: =Data!E2 | E5: =ROUND(Data!E2/Data!C2*100,2) | F5: n/a | G5: =ROUND(Data!H2/Data!F2*100,2) | H5: n/a | I5: =ROUND(Data!F2/Data!G2,2) | J5: =ROUND(Data!K2/Data!B2,2) | K5: n/a
A6: =Data!A3 | B6: =Data!C3 | C6: =Data!D3 | D6: =Data!E3 | E6: =ROUND(Data!E3/Data!C3*100,2) | F6: =IF(E6>E5,"up",IF(E6<E5,"down","flat")) | G6: =ROUND(Data!H3/Data!F3*100,2) | H6: =IF(G6>G5,"up",IF(G6<G5,"down","flat")) | I6: =ROUND(Data!F3/Data!G3,2) | J6: =ROUND(Data!K3/Data!B3,2) | K6: =IF(J6>J5,"up",IF(J6<J5,"down","flat"))
A7: =Data!A4 | B7: =Data!C4 | C7: =Data!D4 | D7: =Data!E4 | E7: =ROUND(Data!E4/Data!C4*100,2) | F7: =IF(E7>E6,"up",IF(E7<E6,"down","flat")) | G7: =ROUND(Data!H4/Data!F4*100,2) | H7: =IF(G7>G6,"up",IF(G7<G6,"down","flat")) | I7: =ROUND(Data!F4/Data!G4,2) | J7: =ROUND(Data!K4/Data!B4,2) | K7: =IF(J7>J6,"up",IF(J7<J6,"down","flat"))
A8: =Data!A5 | B8: =Data!C5 | C8: =Data!D5 | D8: =Data!E5 | E8: =ROUND(Data!E5/Data!C5*100,2) | F8: =IF(E8>E7,"up",IF(E8<E7,"down","flat")) | G8: =ROUND(Data!H5/Data!F5*100,2) | H8: =IF(G8>G7,"up",IF(G8<G7,"down","flat")) | I8: =ROUND(Data!F5/Data!G5,2) | J8: =ROUND(Data!K5/Data!B5,2) | K8: =IF(J8>J7,"up",IF(J8<J7,"down","flat"))
A9: =Data!A6 | B9: =Data!C6 | C9: =Data!D6 | D9: =Data!E6 | E9: =ROUND(Data!E6/Data!C6*100,2) | F9: =IF(E9>E8,"up",IF(E9<E8,"down","flat")) | G9: =ROUND(Data!H6/Data!F6*100,2) | H9: =IF(G9>G8,"up",IF(G9<G8,"down","flat")) | I9: =ROUND(Data!F6/Data!G6,2) | J9: =ROUND(Data!K6/Data!B6,2) | K9: =IF(J9>J8,"up",IF(J9<J8,"down","flat"))
A10: =Data!A7 | B10: =Data!C7 | C10: =Data!D7 | D10: =Data!E7 | E10: =ROUND(Data!E7/Data!C7*100,2) | F10: =IF(E10>E9,"up",IF(E10<E9,"down","flat")) | G10: =ROUND(Data!H7/Data!F7*100,2) | H10: =IF(G10>G9,"up",IF(G10<G9,"down","flat")) | I10: =ROUND(Data!F7/Data!G7,2) | J10: =ROUND(Data!K7/Data!B7,2) | K10: =IF(J10>J9,"up",IF(J10<J9,"down","flat"))
A11: =Data!A8 | B11: =Data!C8 | C11: =Data!D8 | D11: =Data!E8 | E11: =ROUND(Data!E8/Data!C8*100,2) | F11: =IF(E11>E10,"up",IF(E11<E10,"down","flat")) | G11: =ROUND(Data!H8/Data!F8*100,2) | H11: =IF(G11>G10,"up",IF(G11<G10,"down","flat")) | I11: =ROUND(Data!F8/Data!G8,2) | J11: =ROUND(Data!K8/Data!B8,2) | K11: =IF(J11>J10,"up",IF(J11<J10,"down","flat"))
A12: =Data!A9 | B12: =Data!C9 | C12: =Data!D9 | D12: =Data!E9 | E12: =ROUND(Data!E9/Data!C9*100,2) | F12: =IF(E12>E11,"up",IF(E12<E11,"down","flat")) | G12: =ROUND(Data!H9/Data!F9*100,2) | H12: =IF(G12>G11,"up",IF(G12<G11,"down","flat")) | I12: =ROUND(Data!F9/Data!G9,2) | J12: =ROUND(Data!K9/Data!B9,2) | K12: =IF(J12>J11,"up",IF(J12<J11,"down","flat"))
A13: =Data!A10 | B13: =Data!C10 | C13: =Data!D10 | D13: =Data!E10 | E13: =ROUND(Data!E10/Data!C10*100,2) | F13: =IF(E13>E12,"up",IF(E13<E12,"down","flat")) | G13: =ROUND(Data!H10/Data!F10*100,2) | H13: =IF(G13>G12,"up",IF(G13<G12,"down","flat")) | I13: =ROUND(Data!F10/Data!G10,2) | J13: =ROUND(Data!K10/Data!B10,2) | K13: =IF(J13>J12,"up",IF(J13<J12,"down","flat"))
A14: =Data!A11 | B14: =Data!C11 | C14: =Data!D11 | D14: =Data!E11 | E14: =ROUND(Data!E11/Data!C11*100,2) | F14: =IF(E14>E13,"up",IF(E14<E13,"down","flat")) | G14: =ROUND(Data!H11/Data!F11*100,2) | H14: =IF(G14>G13,"up",IF(G14<G13,"down","flat")) | I14: =ROUND(Data!F11/Data!G11,2) | J14: =ROUND(Data!K11/Data!B11,2) | K14: =IF(J14>J13,"up",IF(J14<J13,"down","flat"))
A16: Sector totals, 2015 to 2024
A17: Total income ($) | B17: =SUM(Data!C2:C11)
A18: Total expenses ($) | B18: =SUM(Data!D2:D11)
A19: Total net income ($) | B19: =SUM(Data!E2:E11)
A20: Overall operating margin (%) | B20: =ROUND(SUM(Data!E2:E11)/SUM(Data!C2:C11)*100,2)
A22: Headline
A23: Latest report year | B23: =A14
A24: Operating margin (%) | B24: =E14
A25: Margin direction | B25: =F14
A26: Equity ratio (%) | B26: =G14
A27: Equity ratio direction | B27: =H14
A28: Solvency (assets / liabilities) | B28: =I14
A29: Employees per reporting co-op | B29: =J14
A30: Employees direction | B30: =K14
